keras_video/__init__.py
keras_video/flow.py
keras_video/generator.py
keras_video/sliding.py
keras_video/utils.py
keras_video_generators_modified-0.2.dist-info/LICENSE
keras_video_generators_modified-0.2.dist-info/METADATA
keras_video_generators_modified-0.2.dist-info/WHEEL
keras_video_generators_modified-0.2.dist-info/top_level.txt
keras_video_generators_modified-0.2.dist-info/RECORD
