Metadata-Version: 2.1
Name: keras-video-generators-modified
Version: 0.2
Summary: Keras sequence generators for video data
Home-page: UNKNOWN
Author: Moumita Sen
Author-email: moumitactg@gmail.com
License: MIT
Platform: UNKNOWN
License-File: LICENSE
Requires-Dist: keras (==2.5.0rc0)
Requires-Dist: numpy
Requires-Dist: opencv-python
Requires-Dist: matplotlib
